log2kusto/__init__.py
log2kusto/kusto_handler.py
tests/__init__.py
tests/test_logger.py
log2kusto-0.1.4.dist-info/METADATA
log2kusto-0.1.4.dist-info/WHEEL
log2kusto-0.1.4.dist-info/top_level.txt
log2kusto-0.1.4.dist-info/RECORD
