Metadata-Version: 2.1
Name: log2kusto
Version: 0.1.4
Summary: Logging handler module that writes the logs to Kusto database.
Home-page: https://github.com/pradiptade/log2kusto
Author: Pradipta De
Author-email: pradipta.de@gmail.com
